pyroy/__init__.py
pyroy/checkers.py
pyroy/coders.py
pyroy/decorators.py
pyroy/errors.py
pyroy/fields.py
pyroy/inspectors.py
pyroy/mappers.py
pyroy/models.py
pyroy/parsers.py
pyroy/py.typed
pyroy/regexp.py
pyroy/typedefs.py
pyroy/validators.py
pyroy-0.1.dev0.dist-info/LICENSE
pyroy-0.1.dev0.dist-info/WHEEL
pyroy-0.1.dev0.dist-info/METADATA
pyroy-0.1.dev0.dist-info/RECORD
