Metadata-Version: 2.1
Name: pyroy
Version: 0.1.dev0
Summary: 
Home-page: https://pypi.org/project/pyroy
License: MIT
Keywords: pyroy
Author: Ruslan Ilyasovich Gilfanov
Author-email: ri.gilfanov@yandex.ru
Maintainer: Ruslan Ilyasovich Gilfanov
Maintainer-email: ri.gilfanov@yandex.ru
Requires-Python: >=3.10,<4.0
Classifier: Development Status :: 2 - Pre-Alpha
Classifier: Intended Audience :: Developers
Classifier: License :: OSI Approved :: MIT License
Classifier: Operating System :: OS Independent
Classifier: Programming Language :: Python
Classifier: Programming Language :: Python :: 3
Classifier: Programming Language :: Python :: 3.10
Classifier: Topic :: Software Development
Classifier: Topic :: Software Development :: Libraries
Classifier: Topic :: Software Development :: Libraries :: Python Modules
Classifier: Topic :: Utilities
Classifier: Typing :: Typed
Requires-Dist: typing_extensions (>=4.0.1)
Project-URL: Documentation, https://pyroy.readthedocs.io
Project-URL: Repository, https://github.com/cslibs/pyroy
